ekosis/__init__.py
ekosis/application_base.py
ekosis/cacheing/__init__.py
ekosis/cacheing/cached_item.py
ekosis/cacheing/lru_cache.py
ekosis/cacheing/ttl_cache.py
ekosis/cli/__init__.py
ekosis/cli/argparse_formatter.py
ekosis/cli/bem.py
ekosis/cli/bsm.py
ekosis/cli/log.py
ekosis/cli/qem.py
ekosis/cli/qsm.py
ekosis/cli/shared_argument_parser.py
ekosis/cli/shared_functions.py
ekosis/cli/shared_queue_argument_parser.py
ekosis/cli/stat.py
ekosis/cli/senders/__init__.py
ekosis/cli/senders/buffered_endpoint_management.py
ekosis/cli/senders/buffered_sender_management.py
ekosis/cli/senders/log.py
ekosis/cli/senders/queue_management_sender_base.py
ekosis/cli/senders/queued_endpoint_management.py
ekosis/cli/senders/queued_sender_management.py
ekosis/cli/senders/statistics.py
ekosis/clients/__init__.py
ekosis/clients/client_base.py
ekosis/clients/datagram_client_base.py
ekosis/clients/persistent_stream_client_base.py
ekosis/clients/stream_client_base.py
ekosis/clients/json/__init__.py
ekosis/clients/json/persisted_tcp.py
ekosis/clients/json/persisted_uds.py
ekosis/clients/json/tcp.py
ekosis/clients/json/transient_tcp.py
ekosis/clients/json/transient_uds.py
ekosis/clients/json/udp.py
ekosis/clients/json/uds.py
ekosis/command_line_tool/__init__.py
ekosis/command_line_tool/argument_parser.py
ekosis/command_line_tool/cli.py
ekosis/command_line_tool/senders/__init__.py
ekosis/command_line_tool/senders/eco_statistics_get.py
ekosis/command_line_tool/senders/queued_endpoint_management.py
ekosis/command_line_tool/senders/queued_management_sender_base.py
ekosis/command_line_tool/senders/queued_sender_management.py
ekosis/configuration/__init__.py
ekosis/configuration/argument_parser.py
ekosis/configuration/config_models.py
ekosis/data_transfer_objects/__init__.py
ekosis/data_transfer_objects/buffered_endpoint_response.py
ekosis/data_transfer_objects/empty.py
ekosis/data_transfer_objects/error_states.py
ekosis/data_transfer_objects/json_protocol.py
ekosis-0.14.0.dist-info/licenses/LICENSE
ekosis-0.14.0.dist-info/METADATA
ekosis-0.14.0.dist-info/WHEEL
ekosis-0.14.0.dist-info/top_level.txt
ekosis-0.14.0.dist-info/RECORD
