Metadata-Version: 2.4
Name: ekosis
Version: 0.14.0
Summary: A Python framework for creating message-based, distributed systems. Allowing for TCP, UDP and UDS communications. Using JSON as the communications protocol.
Home-page: https://github.com/TheLastCylon/ecosystem
Author: Dirk Botha
Author-email: bothadj@gmail.com
License: BSD-3-Clause
Classifier: Development Status :: 4 - Beta
Classifier: Intended Audience :: Developers
Classifier: License :: OSI Approved :: BSD License
Classifier: Programming Language :: Python :: 3.11
Requires-Python: >=3.11.4
License-File: LICENSE
Requires-Dist: sqlalchemy>=2.0.31
Requires-Dist: pydantic>=2.8.2
Requires-Dist: numpy>=2.0.0
Dynamic: author
Dynamic: author-email
Dynamic: classifier
Dynamic: description
Dynamic: description-content-type
Dynamic: home-page
Dynamic: license
Dynamic: license-file
Dynamic: requires-dist
Dynamic: requires-python
Dynamic: summary
